model_train/__init__.py
model_train/config.py
model_train/data_loading.py
model_train/func.py
model_train/pipeline_infer.py
model_train/pipeline_train.py
model_train/upload_model.py
model_train-0.0.7.dist-info/METADATA
model_train-0.0.7.dist-info/WHEEL
model_train-0.0.7.dist-info/licenses/LICENSE
model_train-0.0.7.dist-info/RECORD
