Metadata-Version: 2.4
Name: model_train
Version: 0.0.7
Summary: A optimize model inference package
Project-URL: Homepage, https://gitlab.com/sp-saas/vn/product-and-engineering/bi-kevin/model_train
Project-URL: Bug Tracker, https://gitlab.com/sp-saas/vn/product-and-engineering/bi-kevin/model_train/-/issues
Author-email: Kevin Khang <kevinkhang2909@gmail.com>
License: Copyright (c) 2024 Kevin Khang
License-File: LICENSE
Keywords: inference, transformers
Classifier: License :: OSI Approved :: MIT License
Classifier: Operating System :: OS Independent
Classifier: Programming Language :: Python :: 3
Requires-Python: >=3.12
Requires-Dist: accelerate
Requires-Dist: datasets
Requires-Dist: einops
Requires-Dist: peft
Requires-Dist: torch
Requires-Dist: transformers
